MANIFEST.in
README.rst
setup.py
collective/__init__.py
collective.rtvideo.youtube.egg-info/PKG-INFO
collective.rtvideo.youtube.egg-info/SOURCES.txt
collective.rtvideo.youtube.egg-info/dependency_links.txt
collective.rtvideo.youtube.egg-info/entry_points.txt
collective.rtvideo.youtube.egg-info/namespace_packages.txt
collective.rtvideo.youtube.egg-info/not-zip-safe
collective.rtvideo.youtube.egg-info/requires.txt
collective.rtvideo.youtube.egg-info/top_level.txt
collective/rtvideo/__init__.py
collective/rtvideo/youtube/__init__.py
collective/rtvideo/youtube/configure.zcml
collective/rtvideo/youtube/browser/__init__.py
collective/rtvideo/youtube/browser/configure.zcml
collective/rtvideo/youtube/browser/videoembedcode.py
collective/rtvideo/youtube/browser/youtubeembedcode_template.pt
collective/rtvideo/youtube/tests/__init__.py
collective/rtvideo/youtube/tests/base.py
collective/rtvideo/youtube/tests/test_get_thumb.py
collective/rtvideo/youtube/tests/test_videoembedcode.py
docs/HISTORY.rst
docs/INSTALL.txt
docs/LICENSE.GPL
docs/LICENSE.txt